vclocal/__init__.py
vclocal/resources.py
vclocal/subsystem/__init__.py
vclocal/subsystem/common/__init__.py
vclocal/subsystem/common/endereco/__init__.py
vclocal/subsystem/common/endereco/resource.py
vclocal/subsystem/parametrizacao/__init__.py
vclocal/subsystem/parametrizacao/localidade/__init__.py
vclocal/subsystem/parametrizacao/localidade/mesorregiao/__init__.py
vclocal/subsystem/parametrizacao/localidade/mesorregiao/resource.py
vclocal/subsystem/parametrizacao/localidade/microrregiao/__init__.py
vclocal/subsystem/parametrizacao/localidade/microrregiao/resource.py
vclocal/subsystem/parametrizacao/localidade/municipio/__init__.py
vclocal/subsystem/parametrizacao/localidade/municipio/resource.py
vclocal/subsystem/parametrizacao/localidade/regiao/__init__.py
vclocal/subsystem/parametrizacao/localidade/regiao/resource.py
vclocal/subsystem/parametrizacao/localidade/uf/__init__.py
vclocal/subsystem/parametrizacao/localidade/uf/resource.py
vclocal/subsystem/sysadmin/__init__.py
vclocal/subsystem/sysadmin/ibge_sync/__init__.py
vclocal/subsystem/sysadmin/ibge_sync/manager.py
vclocal/subsystem/sysadmin/ibge_sync/resource.py
vclocal-1.0.0.dist-info/AUTHORS
vclocal-1.0.0.dist-info/METADATA
vclocal-1.0.0.dist-info/WHEEL
vclocal-1.0.0.dist-info/top_level.txt
vclocal-1.0.0.dist-info/RECORD
